pyeviews/__init__.py
pyeviews-1.0.5.dist-info/LICENSE.txt
pyeviews-1.0.5.dist-info/METADATA
pyeviews-1.0.5.dist-info/WHEEL
pyeviews-1.0.5.dist-info/top_level.txt
pyeviews-1.0.5.dist-info/RECORD
