Metadata-Version: 2.1
Name: pyeviews
Version: 1.0.5
Summary: Data import/export and EViews function calls from Python
Home-page: https://github.com/bexer/pyeviews
Author: IHS EViews
Author-email: pyeviews@yahoo.com
License: GPLv3
Keywords: eviews econometrics
Classifier: Development Status :: 5 - Production/Stable
Classifier: License :: OSI Approved :: GNU General Public License v3 (GPLv3)
Classifier: Topic :: Scientific/Engineering :: Information Analysis
Classifier: Programming Language :: Python :: 3
Classifier: Operating System :: Microsoft :: Windows
License-File: LICENSE.txt
Requires-Dist: comtypes
Requires-Dist: numpy
Requires-Dist: pandas
